pylsl/__init__.py
pylsl/pylsl.py
pylsl/version.py
pylsl/examples/GetTimeCorrection.py
pylsl/examples/HandleMetadata.py
pylsl/examples/PerformanceTest.py
pylsl/examples/ReceiveAndPlot.py
pylsl/examples/ReceiveData.py
pylsl/examples/ReceiveDataInChunks.py
pylsl/examples/ReceiveStringMarkers.py
pylsl/examples/SendData.py
pylsl/examples/SendDataAdvanced.py
pylsl/examples/SendStringMarkers.py
pylsl/examples/__init__.py
pylsl/lib/liblsl.so
pylsl_coral-0.1.15.0.dist-info/LICENSE
pylsl_coral-0.1.15.0.dist-info/METADATA
pylsl_coral-0.1.15.0.dist-info/WHEEL
pylsl_coral-0.1.15.0.dist-info/top_level.txt
pylsl_coral-0.1.15.0.dist-info/RECORD
