Metadata-Version: 2.1
Name: pylsl-coral
Version: 0.1.15.0
Summary: Python interface to the Lab Streaming Layer
Home-page: https://github.com/labstreaminglayer/liblsl-Python
Author: Christian Kothe
Author-email: christiankothe@gmail.com
License: MIT
Keywords: networking lsl lab streaming layer labstreaminglayer data acquisition
Platform: UNKNOWN
Classifier: Development Status :: 5 - Production/Stable
Classifier: Intended Audience :: Developers
Classifier: Intended Audience :: Science/Research
Classifier: Topic :: System :: Networking
Classifier: Topic :: Scientific/Engineering
Classifier: License :: OSI Approved :: MIT License
Classifier: Operating System :: Microsoft :: Windows
Classifier: Operating System :: POSIX :: Linux
Classifier: Operating System :: MacOS
Classifier: Programming Language :: Python :: 2
Classifier: Programming Language :: Python :: 3
License-File: LICENSE
